oakutils/__init__.py
oakutils/_api_camera.py
oakutils/_legacy_camera.py
oakutils/_webcam.py
oakutils/py.typed
oakutils/aruco/__init__.py
oakutils/aruco/finder.py
oakutils/aruco/localizer.py
oakutils/aruco/stream.py
oakutils/benchmark/__init__.py
oakutils/benchmark/_latency.py
oakutils/benchmark/_throughput.py
oakutils/blobs/__init__.py
oakutils/blobs/_analysis.py
oakutils/blobs/_benchmark.py
oakutils/blobs/_find.py
oakutils/blobs/_cache/__init__.py
oakutils/blobs/_compiler/__init__.py
oakutils/blobs/_compiler/blob.py
oakutils/blobs/_compiler/compile.py
oakutils/blobs/_compiler/onnx.py
oakutils/blobs/_compiler/paths.py
oakutils/blobs/_compiler/torch.py
oakutils/blobs/_compiler/utils.py
oakutils/blobs/definitions/__init__.py
oakutils/blobs/definitions/abstract_model.py
oakutils/blobs/definitions/closing.py
oakutils/blobs/definitions/dilation.py
oakutils/blobs/definitions/erosion.py
oakutils/blobs/definitions/gaussian.py
oakutils/blobs/definitions/gftt.py
oakutils/blobs/definitions/harris.py
oakutils/blobs/definitions/hessian.py
oakutils/blobs/definitions/laplacian.py
oakutils/blobs/definitions/laserscan.py
oakutils/blobs/definitions/opening.py
oakutils/blobs/definitions/point_cloud.py
oakutils/blobs/definitions/sobel.py
oakutils/blobs/definitions/utils/__init__.py
oakutils/blobs/definitions/utils/conversion.py
oakutils/blobs/definitions/utils/custom_types.py
oakutils/blobs/models/__init__.py
oakutils/blobs/models/bulk.py
oakutils/blobs/models/shave1/GFTTBlurGray_11x11_shaves1.blob
oakutils/blobs/models/shave1/GFTTBlurGray_13x13_shaves1.blob
oakutils/blobs/models/shave1/GFTTBlurGray_15x15_shaves1.blob
oakutils/blobs/models/shave1/GFTTBlurGray_3x3_shaves1.blob
oakutils/blobs/models/shave1/GFTTBlurGray_5x5_shaves1.blob
oakutils/blobs/models/shave1/GFTTBlurGray_7x7_shaves1.blob
oakutils/blobs/models/shave1/GFTTBlurGray_9x9_shaves1.blob
oakutils/blobs/models/shave1/GFTTBlur_11x11_shaves1.blob
oakutils/blobs/models/shave1/GFTTBlur_13x13_shaves1.blob
oakutils-1.6.0.dist-info/LICENSE
oakutils-1.6.0.dist-info/METADATA
oakutils-1.6.0.dist-info/WHEEL
oakutils-1.6.0.dist-info/top_level.txt
oakutils-1.6.0.dist-info/RECORD
