Metadata-Version: 2.1
Name: oakutils
Version: 1.6.0
Author-email: Justin Davis <davisjustin302@gmail.com>
Maintainer-email: Justin Davis <davisjustin302@gmail.com>
Project-URL: Homepage, https://github.com/justincdavis/oakutils
Project-URL: Bug Tracker, https://github.com/justincdavis/oakutils/issues
Classifier: Development Status :: 4 - Beta
Classifier: Programming Language :: Python :: 3 :: Only
Classifier: Programming Language :: Python :: 3
Classifier: Programming Language :: Python :: 3.8
Classifier: Programming Language :: Python :: 3.9
Classifier: Programming Language :: Python :: 3.10
Classifier: Programming Language :: Python :: 3.11
Classifier: Programming Language :: Python :: 3.12
Classifier: Programming Language :: Python :: Implementation :: CPython
Classifier: License :: OSI Approved :: MIT License
Classifier: Operating System :: Microsoft :: Windows
Classifier: Operating System :: POSIX :: Linux
Classifier: Operating System :: MacOS
Classifier: Natural Language :: English
Classifier: Topic :: System :: Hardware
Classifier: Topic :: Scientific/Engineering
Classifier: Topic :: Scientific/Engineering :: Artificial Intelligence
Classifier: Topic :: Scientific/Engineering :: Image Processing
Classifier: Topic :: Scientific/Engineering :: Image Recognition
Classifier: Topic :: Software Development
Classifier: Topic :: Software Development :: Embedded Systems
Classifier: Topic :: Software Development :: Libraries
Classifier: Topic :: System :: Hardware
Classifier: Intended Audience :: Developers
Classifier: Intended Audience :: Education
Classifier: Intended Audience :: Science/Research
Classifier: Intended Audience :: Education
Classifier: Intended Audience :: Information Technology
Classifier: Intended Audience :: End Users/Desktop
Classifier: Typing :: Typed
Requires-Python: <3.13,>=3.8
License-File: LICENSE
Requires-Dist: depthai >=2.24
Requires-Dist: numpy <2.0,>=1.20
Requires-Dist: opencv-contrib-python >=4.9.0
Requires-Dist: cv2ext >=0.0.10
Requires-Dist: typing-extensions >=4.9.0
Requires-Dist: setuptools >=57.0.0
Provides-Extra: ci
Requires-Dist: ruff >=0.5.6 ; extra == 'ci'
Requires-Dist: mypy >=1.11.1 ; extra == 'ci'
Requires-Dist: types-setuptools >=57.0.0 ; extra == 'ci'
Requires-Dist: types-requests >=2.25.0 ; extra == 'ci'
Provides-Extra: compiler
Requires-Dist: kornia >=0.6.0 ; extra == 'compiler'
Requires-Dist: torch >=1.9.0 ; extra == 'compiler'
Requires-Dist: onnx >=1.15.0 ; extra == 'compiler'
Requires-Dist: onnxruntime >=1.15.0 ; extra == 'compiler'
Requires-Dist: onnxsim >=0.4.33 ; extra == 'compiler'
Requires-Dist: blobconverter ==1.4.3 ; extra == 'compiler'
Requires-Dist: requests >=2.25.0 ; extra == 'compiler'
Requires-Dist: boto3 >=1.34.37 ; extra == 'compiler'
Requires-Dist: botocore >=1.34.37 ; extra == 'compiler'
Provides-Extra: dev
Requires-Dist: oakutils[o3d] ; extra == 'dev'
Requires-Dist: oakutils[compiler] ; extra == 'dev'
Requires-Dist: oakutils[ci] ; extra == 'dev'
Requires-Dist: oakutils[test] ; extra == 'dev'
Requires-Dist: oakutils[docs] ; extra == 'dev'
Requires-Dist: twine >=4.0.0 ; extra == 'dev'
Requires-Dist: wheel >=0.37.0 ; extra == 'dev'
Requires-Dist: bumpver >=2023.1126 ; extra == 'dev'
Requires-Dist: pyclean >=2.7.0 ; extra == 'dev'
Requires-Dist: pyright >=1.1.348 ; extra == 'dev'
Provides-Extra: docs
Requires-Dist: sphinx ==6.2.1 ; extra == 'docs'
Requires-Dist: sphinx-rtd-theme ==2.0.0 ; extra == 'docs'
Requires-Dist: myst-parser ==1.0.0 ; extra == 'docs'
Provides-Extra: o3d
Requires-Dist: open3d >=0.18.0 ; extra == 'o3d'
Provides-Extra: test
Requires-Dist: pytest >=6.2.0 ; extra == 'test'
Requires-Dist: stdlib-list >=0.10.0 ; extra == 'test'
